LICENSE
MANIFEST.in
README.rst
setup.py
scipion_em_sll.egg-info/PKG-INFO
scipion_em_sll.egg-info/SOURCES.txt
scipion_em_sll.egg-info/dependency_links.txt
scipion_em_sll.egg-info/top_level.txt
sll/__init__.py
sll/bibtex.py
sll/constants.py
sll/convert.py
sll/viewers.py
sll/protocols/__init__.py
sll/protocols/protocol_filter_classes.py
sll/protocols/protocol_filter_classes_cc.py
sll/protocols/protocol_filter_ctf.py
sll/protocols/protocol_filter_ctf_threshold.py
sll/tests/__init__.py
sll/tests/test_protocols_sll.py