Metadata-Version: 1.1
Name: scipion-em-sll
Version: 0.0.1
Summary: Scipion plugin for CryoEM tools developed at SciLifeLab
Home-page: https://github.com/3dem/scipion-em-sll
Author: J.M. De la Rosa Trevin
Author-email: delarosatrevin@scilifelab.se
License: UNKNOWN
Project-URL: Source, https://github.com/3dem/scipion-em-sll/
Project-URL: Bug Reports, https://github.com/3dem/scipion-em-sll/issues
Keywords: scipion electron-microscopy cryo-em structural-biology image-processing scipion-2.0
Platform: UNKNOWN
Classifier: Development Status :: 3 - Alpha
Classifier: License :: OSI Approved :: GNU General Public License v3 (GPLv3)
Classifier: Programming Language :: Python :: 2.7
